am_imaging/__init__.py
am_imaging/files/__init__.py
am_imaging/video/__init__.py
am_imaging/video/__main__.py
am_imaging/video/frame_selection.py
video/__init__.py
video/frame_selection.py
am_imaging-0.1.5.dist-info/METADATA
am_imaging-0.1.5.dist-info/WHEEL
am_imaging-0.1.5.dist-info/top_level.txt
am_imaging-0.1.5.dist-info/RECORD
