Metadata-Version: 2.1
Name: am-imaging
Version: 0.1.5
Summary: Utility functionse for processing images and video
Author: Aaron Moffatt, GPT
Author-email: a@airvr.studio
Requires-Dist: numpy
Requires-Dist: opencv-python
